CHANGELOG.txt
LICENSE.txt
MANIFEST.in
README.txt
setup.py
backupdb/__init__.py
backupdb/apps.py
backupdb/settings.py
backupdb/dbconnect/__init__.py
backupdb/dbconnect/base.py
backupdb/dbconnect/mysql.py
backupdb/management/__init__.py
backupdb/management/commands/__init__.py
backupdb/management/commands/add_users.py
backupdb/management/commands/backupdb.py
backupdb/management/commands/del_users.py
backupdb/management/commands/dumpdb.py
backupdb/management/commands/style_list.py
backupdb/migrations/__init__.py
mysqldump.egg-info/PKG-INFO
mysqldump.egg-info/SOURCES.txt
mysqldump.egg-info/dependency_links.txt
mysqldump.egg-info/requires.txt
mysqldump.egg-info/top_level.txt